codist/__init__.py
codist/ast.py
codist/distance.py
codist/tree.py
codist-0.2.1.dist-info/LICENSE
codist-0.2.1.dist-info/METADATA
codist-0.2.1.dist-info/WHEEL
codist-0.2.1.dist-info/top_level.txt
codist-0.2.1.dist-info/RECORD
