Metadata-Version: 2.1
Name: codist
Version: 0.2.1
Summary: AST edit distance
License: MIT License
Project-URL: repository, https://github.com/James-Ansley/codist
Classifier: Development Status :: 1 - Planning
Classifier: Topic :: Utilities
Classifier: Programming Language :: Python :: 3
Classifier: License :: OSI Approved :: MIT License
Requires-Python: >=3.12
License-File: LICENSE
